odoo10_addon_connector_magento_firstname-10.0.1.0.0-py2.7-nspkg.pth
odoo/addons/connector_magento_firstname/README.rst
odoo/addons/connector_magento_firstname/__init__.py
odoo/addons/connector_magento_firstname/__manifest__.py
odoo/addons/connector_magento_firstname/models/__init__.py
odoo/addons/connector_magento_firstname/models/partner.py
odoo10_addon_connector_magento_firstname-10.0.1.0.0.dist-info/DESCRIPTION.rst
odoo10_addon_connector_magento_firstname-10.0.1.0.0.dist-info/METADATA
odoo10_addon_connector_magento_firstname-10.0.1.0.0.dist-info/RECORD
odoo10_addon_connector_magento_firstname-10.0.1.0.0.dist-info/WHEEL
odoo10_addon_connector_magento_firstname-10.0.1.0.0.dist-info/metadata.json
odoo10_addon_connector_magento_firstname-10.0.1.0.0.dist-info/namespace_packages.txt
odoo10_addon_connector_magento_firstname-10.0.1.0.0.dist-info/top_level.txt
